{
  "9": {
    "upgradeSpend": 240,
    "id": 9
  },
  "1": {},
  "8": {
    "upgradeSpend": 200,
    "id": 8,
    "skillEffect": 1,
    "skillType": 3
  },
  "7": {
    "upgradeSpend": 160,
    "id": 7,
    "skillType": 4
  },
  "4": {
    "upgradeSpend": 40,
    "id": 4,
    "skillEffect": 3,
    "skillType": 3
  },
  "5": {
    "upgradeSpend": 80,
    "id": 5
  },
  "2": {
    "upgradeSpend": 20,
    "id": 2,
    "skillType": 2
  },
  "3": {
    "upgradeSpend": 30,
    "id": 3,
    "skillType": 4
  },
  "15": {
    "upgradeSpend": 1680,
    "id": 15,
    "skillType": 4
  },
  "14": {
    "upgradeSpend": 1440,
    "id": 14,
    "skillType": 2
  },
  "13": {
    "upgradeSpend": 1200,
    "id": 13
  },
  "12": {
    "upgradeSpend": 960,
    "id": 12,
    "skillEffect": 1,
    "skillType": 3
  },
  "6": {
    "upgradeSpend": 120,
    "id": 6,
    "skillType": 2
  },
  "16": {
    "upgradeSpend": 1920,
    "id": 16,
    "skillEffect": 1,
    "skillType": 3
  },
  "10": {
    "upgradeSpend": 480,
    "id": 10,
    "skillType": 2
  },
  "11": {
    "upgradeSpend": 720,
    "id": 11,
    "skillType": 4
  }
}